main.py
truenas_backup-1.0.0.dist-info/licenses/LICENSE
truenas_backup-1.0.0.dist-info/METADATA
truenas_backup-1.0.0.dist-info/WHEEL
truenas_backup-1.0.0.dist-info/entry_points.txt
truenas_backup-1.0.0.dist-info/top_level.txt
truenas_backup-1.0.0.dist-info/RECORD
