Metadata-Version: 2.4
Name: truenas-backup
Version: 1.0.0
Summary: CLI tool for backing up TrueNAS configurations.
Author-email: Shagit Ziganshin <theLastOfCats@gmail.com>
License-Expression: MIT
Requires-Python: >=3.12
License-File: LICENSE
Requires-Dist: loguru>=0.7.3
Requires-Dist: python-dotenv>=1.1.1
Requires-Dist: requests>=2.32.5
Requires-Dist: truenas-api-client
Requires-Dist: typer>=0.20.0
Dynamic: license-file
